{
	"name":"Unsplash",
	"lastLogin":"",
	"home":"https://unsplash.com",
	"connect":{
		
		"todo":[
			{"action":"goto", "url":"https://unsplash.com/login"},
			{"action":"fill", "what":"login", "search":"#user_email", "grave":true},
			{"action":"fill", "what":"password", "search":"#user_password", "grave":true},
			{
				"action": "click",
				"search": "button[data-test='login-button']"
			}
			]
	},
	"Facebook":{
		"todo":[
			{"action":"goto", "url":"https://unsplash.com/login"},
			{"action":"aclick" , "search":"a[href*='facebook']"}
		]
	},
	"logout":{
		"todo":[
			{"action":"goto", "url":"https://unsplash.com/logout"},
			{"action":"waitload"}
			]
	},
	"checkAlreadyLogged":[
		{"search":"a[href*='/likes']"}
	]
}