{
  "name":"Chronodrive",
  "lastLogin":"",
  "home":"https://www.chronodrive.com/",
  "connect":{
    "todo":[
      {"action":"goto", "url":"https://www.chronodrive.com/login"},
      {"action":"fill", "what":"login", "search":"#email_login", "grave":true},
      {"action":"fill", "what":"password", "search":"#pwd_login", "grave":true},
      {"action":"trueClick", "search":"#loginForm button", "grave":true}
    ]
  },
  "checkAlreadyLogged":[
    {"action":"waitfor", "search":"a[href*='logout'], a[href*='login']"},
    {"search":"a[href*='logout']"}
  ],
  "logout":{
    "todo":[
      {"action":"aclick", "search":"a[href*='logout']"}
    ]
  }
}



